{"expireTime":9007200839200138000,"key":"gatsby-plugin-mdx-entire-payload-90de9b35980f7fd53972f866572b0cb8-","val":{"mdast":{"type":"root","children":[{"type":"import","value":"import DefaultLayout from \"/Users/jasonclark/Source/react-table/node_modules/gatsby-theme-docz/src/base/Layout.js\"","position":{"start":{"line":3,"column":1,"offset":2},"end":{"line":3,"column":115,"offset":116},"indent":[]}},{"type":"export","default":true,"value":"export default DefaultLayout","position":{"start":{"line":5,"column":1,"offset":118},"end":{"line":5,"column":29,"offset":146},"indent":[]}},{"type":"heading","depth":1,"children":[{"type":"inlineCode","value":"useBlocklayout","position":{"start":{"line":8,"column":3,"offset":151},"end":{"line":8,"column":19,"offset":167},"indent":[]}}],"position":{"start":{"line":8,"column":1,"offset":149},"end":{"line":8,"column":19,"offset":167},"indent":[]}},{"type":"list","ordered":false,"start":null,"spread":false,"children":[{"type":"listItem","spread":false,"checked":null,"children":[{"type":"paragraph","children":[{"type":"text","value":"Plugin Hook","position":{"start":{"line":10,"column":3,"offset":171},"end":{"line":10,"column":14,"offset":182},"indent":[]}}],"position":{"start":{"line":10,"column":3,"offset":171},"end":{"line":10,"column":14,"offset":182},"indent":[]}}],"position":{"start":{"line":10,"column":1,"offset":169},"end":{"line":10,"column":14,"offset":182},"indent":[]}},{"type":"listItem","spread":false,"checked":null,"children":[{"type":"paragraph","children":[{"type":"text","value":"Optional","position":{"start":{"line":11,"column":3,"offset":185},"end":{"line":11,"column":11,"offset":193},"indent":[]}}],"position":{"start":{"line":11,"column":3,"offset":185},"end":{"line":11,"column":11,"offset":193},"indent":[]}}],"position":{"start":{"line":11,"column":1,"offset":183},"end":{"line":11,"column":11,"offset":193},"indent":[]}}],"position":{"start":{"line":10,"column":1,"offset":169},"end":{"line":11,"column":11,"offset":193},"indent":[1]}},{"type":"paragraph","children":[{"type":"inlineCode","value":"useBlocklayout","position":{"start":{"line":13,"column":1,"offset":195},"end":{"line":13,"column":17,"offset":211},"indent":[]}},{"type":"text","value":" is a plugin hook that adds support for headers and cells to be rendered as ","position":{"start":{"line":13,"column":17,"offset":211},"end":{"line":13,"column":93,"offset":287},"indent":[]}},{"type":"inlineCode","value":"inline-block","position":{"start":{"line":13,"column":93,"offset":287},"end":{"line":13,"column":107,"offset":301},"indent":[]}},{"type":"text","value":" ","position":{"start":{"line":13,"column":107,"offset":301},"end":{"line":13,"column":108,"offset":302},"indent":[]}},{"type":"inlineCode","value":"div","position":{"start":{"line":13,"column":108,"offset":302},"end":{"line":13,"column":113,"offset":307},"indent":[]}},{"type":"text","value":"s (or other non-table elements) with explicit ","position":{"start":{"line":13,"column":113,"offset":307},"end":{"line":13,"column":159,"offset":353},"indent":[]}},{"type":"inlineCode","value":"width","position":{"start":{"line":13,"column":159,"offset":353},"end":{"line":13,"column":166,"offset":360},"indent":[]}},{"type":"text","value":". Similar to the ","position":{"start":{"line":13,"column":166,"offset":360},"end":{"line":13,"column":183,"offset":377},"indent":[]}},{"type":"inlineCode","value":"useAbsoluteLayout","position":{"start":{"line":13,"column":183,"offset":377},"end":{"line":13,"column":202,"offset":396},"indent":[]}},{"type":"text","value":" hook, this becomes useful if and when you need to virtualize rows and cells for performance.","position":{"start":{"line":13,"column":202,"offset":396},"end":{"line":13,"column":295,"offset":489},"indent":[]}}],"position":{"start":{"line":13,"column":1,"offset":195},"end":{"line":13,"column":295,"offset":489},"indent":[]}},{"type":"paragraph","children":[{"type":"strong","children":[{"type":"text","value":"NOTE:","position":{"start":{"line":15,"column":3,"offset":493},"end":{"line":15,"column":8,"offset":498},"indent":[]}}],"position":{"start":{"line":15,"column":1,"offset":491},"end":{"line":15,"column":10,"offset":500},"indent":[]}},{"type":"text","value":" Although no additional options are needed for this plugin to work, the core column options ","position":{"start":{"line":15,"column":10,"offset":500},"end":{"line":15,"column":102,"offset":592},"indent":[]}},{"type":"inlineCode","value":"width","position":{"start":{"line":15,"column":102,"offset":592},"end":{"line":15,"column":109,"offset":599},"indent":[]}},{"type":"text","value":", ","position":{"start":{"line":15,"column":109,"offset":599},"end":{"line":15,"column":111,"offset":601},"indent":[]}},{"type":"inlineCode","value":"minWidth","position":{"start":{"line":15,"column":111,"offset":601},"end":{"line":15,"column":121,"offset":611},"indent":[]}},{"type":"text","value":" and ","position":{"start":{"line":15,"column":121,"offset":611},"end":{"line":15,"column":126,"offset":616},"indent":[]}},{"type":"inlineCode","value":"maxWidth","position":{"start":{"line":15,"column":126,"offset":616},"end":{"line":15,"column":136,"offset":626},"indent":[]}},{"type":"text","value":" are used to calculate column and cell widths and must be set. ","position":{"start":{"line":15,"column":136,"offset":626},"end":{"line":15,"column":199,"offset":689},"indent":[]}},{"type":"link","title":null,"url":"#column-options","children":[{"type":"text","value":"See Column Options","position":{"start":{"line":15,"column":200,"offset":690},"end":{"line":15,"column":218,"offset":708},"indent":[]}}],"position":{"start":{"line":15,"column":199,"offset":689},"end":{"line":15,"column":236,"offset":726},"indent":[]}},{"type":"text","value":" for more information on these options.","position":{"start":{"line":15,"column":236,"offset":726},"end":{"line":15,"column":275,"offset":765},"indent":[]}}],"position":{"start":{"line":15,"column":1,"offset":491},"end":{"line":15,"column":275,"offset":765},"indent":[]}},{"type":"heading","depth":3,"children":[{"type":"text","value":"Row Properties","position":{"start":{"line":17,"column":5,"offset":771},"end":{"line":17,"column":19,"offset":785},"indent":[]}}],"position":{"start":{"line":17,"column":1,"offset":767},"end":{"line":17,"column":19,"offset":785},"indent":[]}},{"type":"list","ordered":false,"start":null,"spread":false,"children":[{"type":"listItem","spread":false,"checked":null,"children":[{"type":"paragraph","children":[{"type":"inlineCode","value":"getRowProps","position":{"start":{"line":19,"column":3,"offset":789},"end":{"line":19,"column":16,"offset":802},"indent":[]}}],"position":{"start":{"line":19,"column":3,"offset":789},"end":{"line":19,"column":16,"offset":802},"indent":[]}},{"type":"list","ordered":false,"start":null,"spread":false,"children":[{"type":"listItem","spread":false,"checked":null,"children":[{"type":"paragraph","children":[{"type":"strong","children":[{"type":"text","value":"Usage Required","position":{"start":{"line":20,"column":7,"offset":809},"end":{"line":20,"column":21,"offset":823},"indent":[]}}],"position":{"start":{"line":20,"column":5,"offset":807},"end":{"line":20,"column":23,"offset":825},"indent":[]}}],"position":{"start":{"line":20,"column":5,"offset":807},"end":{"line":20,"column":23,"offset":825},"indent":[]}}],"position":{"start":{"line":20,"column":3,"offset":805},"end":{"line":20,"column":23,"offset":825},"indent":[]}},{"type":"listItem","spread":false,"checked":null,"children":[{"type":"paragraph","children":[{"type":"text","value":"This core prop getter is required to to enable absolute layout for rows","position":{"start":{"line":21,"column":5,"offset":830},"end":{"line":21,"column":76,"offset":901},"indent":[]}}],"position":{"start":{"line":21,"column":5,"offset":830},"end":{"line":21,"column":76,"offset":901},"indent":[]}}],"position":{"start":{"line":21,"column":3,"offset":828},"end":{"line":21,"column":76,"offset":901},"indent":[]}}],"position":{"start":{"line":20,"column":3,"offset":805},"end":{"line":21,"column":76,"offset":901},"indent":[3]}}],"position":{"start":{"line":19,"column":1,"offset":787},"end":{"line":21,"column":76,"offset":901},"indent":[1,1]}}],"position":{"start":{"line":19,"column":1,"offset":787},"end":{"line":21,"column":76,"offset":901},"indent":[1,1]}},{"type":"heading","depth":3,"children":[{"type":"text","value":"Cell Properties","position":{"start":{"line":23,"column":5,"offset":907},"end":{"line":23,"column":20,"offset":922},"indent":[]}}],"position":{"start":{"line":23,"column":1,"offset":903},"end":{"line":23,"column":20,"offset":922},"indent":[]}},{"type":"list","ordered":false,"start":null,"spread":false,"children":[{"type":"listItem","spread":false,"checked":null,"children":[{"type":"paragraph","children":[{"type":"inlineCode","value":"getCellProps","position":{"start":{"line":25,"column":3,"offset":926},"end":{"line":25,"column":17,"offset":940},"indent":[]}}],"position":{"start":{"line":25,"column":3,"offset":926},"end":{"line":25,"column":17,"offset":940},"indent":[]}},{"type":"list","ordered":false,"start":null,"spread":false,"children":[{"type":"listItem","spread":false,"checked":null,"children":[{"type":"paragraph","children":[{"type":"strong","children":[{"type":"text","value":"Usage Required","position":{"start":{"line":26,"column":7,"offset":947},"end":{"line":26,"column":21,"offset":961},"indent":[]}}],"position":{"start":{"line":26,"column":5,"offset":945},"end":{"line":26,"column":23,"offset":963},"indent":[]}}],"position":{"start":{"line":26,"column":5,"offset":945},"end":{"line":26,"column":23,"offset":963},"indent":[]}}],"position":{"start":{"line":26,"column":3,"offset":943},"end":{"line":26,"column":23,"offset":963},"indent":[]}},{"type":"listItem","spread":false,"checked":null,"children":[{"type":"paragraph","children":[{"type":"text","value":"This core prop getter is required to to enable absolute layout for rows cells","position":{"start":{"line":27,"column":5,"offset":968},"end":{"line":27,"column":82,"offset":1045},"indent":[]}}],"position":{"start":{"line":27,"column":5,"offset":968},"end":{"line":27,"column":82,"offset":1045},"indent":[]}}],"position":{"start":{"line":27,"column":3,"offset":966},"end":{"line":27,"column":82,"offset":1045},"indent":[]}}],"position":{"start":{"line":26,"column":3,"offset":943},"end":{"line":27,"column":82,"offset":1045},"indent":[3]}}],"position":{"start":{"line":25,"column":1,"offset":924},"end":{"line":27,"column":82,"offset":1045},"indent":[1,1]}}],"position":{"start":{"line":25,"column":1,"offset":924},"end":{"line":27,"column":82,"offset":1045},"indent":[1,1]}},{"type":"heading","depth":3,"children":[{"type":"text","value":"HeaderGroup Properties","position":{"start":{"line":29,"column":5,"offset":1051},"end":{"line":29,"column":27,"offset":1073},"indent":[]}}],"position":{"start":{"line":29,"column":1,"offset":1047},"end":{"line":29,"column":27,"offset":1073},"indent":[]}},{"type":"list","ordered":false,"start":null,"spread":false,"children":[{"type":"listItem","spread":false,"checked":null,"children":[{"type":"paragraph","children":[{"type":"inlineCode","value":"getHeaderGroupProps","position":{"start":{"line":31,"column":3,"offset":1077},"end":{"line":31,"column":24,"offset":1098},"indent":[]}}],"position":{"start":{"line":31,"column":3,"offset":1077},"end":{"line":31,"column":24,"offset":1098},"indent":[]}},{"type":"list","ordered":false,"start":null,"spread":false,"children":[{"type":"listItem","spread":false,"checked":null,"children":[{"type":"paragraph","children":[{"type":"strong","children":[{"type":"text","value":"Usage Required","position":{"start":{"line":32,"column":7,"offset":1105},"end":{"line":32,"column":21,"offset":1119},"indent":[]}}],"position":{"start":{"line":32,"column":5,"offset":1103},"end":{"line":32,"column":23,"offset":1121},"indent":[]}}],"position":{"start":{"line":32,"column":5,"offset":1103},"end":{"line":32,"column":23,"offset":1121},"indent":[]}}],"position":{"start":{"line":32,"column":3,"offset":1101},"end":{"line":32,"column":23,"offset":1121},"indent":[]}},{"type":"listItem","spread":false,"checked":null,"children":[{"type":"paragraph","children":[{"type":"text","value":"This core prop getter is required to to enable absolute layout for headers","position":{"start":{"line":33,"column":5,"offset":1126},"end":{"line":33,"column":79,"offset":1200},"indent":[]}}],"position":{"start":{"line":33,"column":5,"offset":1126},"end":{"line":33,"column":79,"offset":1200},"indent":[]}}],"position":{"start":{"line":33,"column":3,"offset":1124},"end":{"line":33,"column":79,"offset":1200},"indent":[]}}],"position":{"start":{"line":32,"column":3,"offset":1101},"end":{"line":33,"column":79,"offset":1200},"indent":[3]}}],"position":{"start":{"line":31,"column":1,"offset":1075},"end":{"line":33,"column":79,"offset":1200},"indent":[1,1]}}],"position":{"start":{"line":31,"column":1,"offset":1075},"end":{"line":33,"column":79,"offset":1200},"indent":[1,1]}},{"type":"heading","depth":3,"children":[{"type":"text","value":"Header Properties","position":{"start":{"line":35,"column":5,"offset":1206},"end":{"line":35,"column":22,"offset":1223},"indent":[]}}],"position":{"start":{"line":35,"column":1,"offset":1202},"end":{"line":35,"column":22,"offset":1223},"indent":[]}},{"type":"list","ordered":false,"start":null,"spread":false,"children":[{"type":"listItem","spread":false,"checked":null,"children":[{"type":"paragraph","children":[{"type":"inlineCode","value":"getHeaderProps","position":{"start":{"line":37,"column":3,"offset":1227},"end":{"line":37,"column":19,"offset":1243},"indent":[]}}],"position":{"start":{"line":37,"column":3,"offset":1227},"end":{"line":37,"column":19,"offset":1243},"indent":[]}},{"type":"list","ordered":false,"start":null,"spread":false,"children":[{"type":"listItem","spread":false,"checked":null,"children":[{"type":"paragraph","children":[{"type":"strong","children":[{"type":"text","value":"Usage Required","position":{"start":{"line":38,"column":7,"offset":1250},"end":{"line":38,"column":21,"offset":1264},"indent":[]}}],"position":{"start":{"line":38,"column":5,"offset":1248},"end":{"line":38,"column":23,"offset":1266},"indent":[]}}],"position":{"start":{"line":38,"column":5,"offset":1248},"end":{"line":38,"column":23,"offset":1266},"indent":[]}}],"position":{"start":{"line":38,"column":3,"offset":1246},"end":{"line":38,"column":23,"offset":1266},"indent":[]}},{"type":"listItem","spread":false,"checked":null,"children":[{"type":"paragraph","children":[{"type":"text","value":"This core prop getter is required to to enable absolute layout for headers","position":{"start":{"line":39,"column":5,"offset":1271},"end":{"line":39,"column":79,"offset":1345},"indent":[]}}],"position":{"start":{"line":39,"column":5,"offset":1271},"end":{"line":39,"column":79,"offset":1345},"indent":[]}}],"position":{"start":{"line":39,"column":3,"offset":1269},"end":{"line":39,"column":79,"offset":1345},"indent":[]}}],"position":{"start":{"line":38,"column":3,"offset":1246},"end":{"line":39,"column":79,"offset":1345},"indent":[3]}}],"position":{"start":{"line":37,"column":1,"offset":1225},"end":{"line":39,"column":79,"offset":1345},"indent":[1,1]}}],"position":{"start":{"line":37,"column":1,"offset":1225},"end":{"line":39,"column":79,"offset":1345},"indent":[1,1]}},{"type":"heading","depth":3,"children":[{"type":"text","value":"Example","position":{"start":{"line":41,"column":5,"offset":1351},"end":{"line":41,"column":12,"offset":1358},"indent":[]}}],"position":{"start":{"line":41,"column":1,"offset":1347},"end":{"line":41,"column":12,"offset":1358},"indent":[]}},{"type":"list","ordered":false,"start":null,"spread":false,"children":[{"type":"listItem","spread":false,"checked":null,"children":[{"type":"paragraph","children":[{"type":"link","title":null,"url":"https://github.com/tannerlinsley/react-table/tree/master/examples/block-layout","children":[{"type":"text","value":"Source","position":{"start":{"line":43,"column":4,"offset":1363},"end":{"line":43,"column":10,"offset":1369},"indent":[]}}],"position":{"start":{"line":43,"column":3,"offset":1362},"end":{"line":43,"column":91,"offset":1450},"indent":[]}}],"position":{"start":{"line":43,"column":3,"offset":1362},"end":{"line":43,"column":91,"offset":1450},"indent":[]}}],"position":{"start":{"line":43,"column":1,"offset":1360},"end":{"line":43,"column":91,"offset":1450},"indent":[]}},{"type":"listItem","spread":false,"checked":null,"children":[{"type":"paragraph","children":[{"type":"link","title":null,"url":"https://codesandbox.io/s/github/tannerlinsley/react-table/tree/master/examples/block-layout","children":[{"type":"text","value":"Open in CodeSandbox","position":{"start":{"line":44,"column":4,"offset":1454},"end":{"line":44,"column":23,"offset":1473},"indent":[]}}],"position":{"start":{"line":44,"column":3,"offset":1453},"end":{"line":44,"column":117,"offset":1567},"indent":[]}}],"position":{"start":{"line":44,"column":3,"offset":1453},"end":{"line":44,"column":117,"offset":1567},"indent":[]}}],"position":{"start":{"line":44,"column":1,"offset":1451},"end":{"line":44,"column":117,"offset":1567},"indent":[]}}],"position":{"start":{"line":43,"column":1,"offset":1360},"end":{"line":44,"column":117,"offset":1567},"indent":[1]}},{"type":"export","value":"export const _frontmatter = {}","position":{"start":{"line":47,"column":1,"offset":1570},"end":{"line":47,"column":31,"offset":1600},"indent":[]}}],"position":{"start":{"line":1,"column":1,"offset":0},"end":{"line":47,"column":31,"offset":1600}}},"scopeImports":[],"scopeIdentifiers":[],"rawMDXOutput":"/* @jsx mdx */\nimport { mdx } from '@mdx-js/react';\n/* @jsx mdx */\nimport DefaultLayout from \"/Users/jasonclark/Source/react-table/node_modules/gatsby-theme-docz/src/base/Layout.js\"\nexport const _frontmatter = {};\nconst makeShortcode = name => function MDXDefaultShortcode(props) {\n  console.warn(\"Component \" + name + \" was not imported, exported, or provided by MDXProvider as global scope\")\n  return <div {...props}/>\n};\n\nconst layoutProps = {\n  _frontmatter\n};\nconst MDXLayout = DefaultLayout\nexport default function MDXContent({\n  components,\n  ...props\n}) {\n  return <MDXLayout {...layoutProps} {...props} components={components} mdxType=\"MDXLayout\">\n\n\n    <h1 {...{\n      \"id\": \"useblocklayout\"\n    }}><inlineCode parentName=\"h1\">{`useBlocklayout`}</inlineCode></h1>\n    <ul>\n      <li parentName=\"ul\">{`Plugin Hook`}</li>\n      <li parentName=\"ul\">{`Optional`}</li>\n    </ul>\n    <p><inlineCode parentName=\"p\">{`useBlocklayout`}</inlineCode>{` is a plugin hook that adds support for headers and cells to be rendered as `}<inlineCode parentName=\"p\">{`inline-block`}</inlineCode>{` `}<inlineCode parentName=\"p\">{`div`}</inlineCode>{`s (or other non-table elements) with explicit `}<inlineCode parentName=\"p\">{`width`}</inlineCode>{`. Similar to the `}<inlineCode parentName=\"p\">{`useAbsoluteLayout`}</inlineCode>{` hook, this becomes useful if and when you need to virtualize rows and cells for performance.`}</p>\n    <p><strong parentName=\"p\">{`NOTE:`}</strong>{` Although no additional options are needed for this plugin to work, the core column options `}<inlineCode parentName=\"p\">{`width`}</inlineCode>{`, `}<inlineCode parentName=\"p\">{`minWidth`}</inlineCode>{` and `}<inlineCode parentName=\"p\">{`maxWidth`}</inlineCode>{` are used to calculate column and cell widths and must be set. `}<a parentName=\"p\" {...{\n        \"href\": \"#column-options\"\n      }}>{`See Column Options`}</a>{` for more information on these options.`}</p>\n    <h3 {...{\n      \"id\": \"row-properties\"\n    }}>{`Row Properties`}</h3>\n    <ul>\n      <li parentName=\"ul\"><inlineCode parentName=\"li\">{`getRowProps`}</inlineCode><ul parentName=\"li\">\n          <li parentName=\"ul\"><strong parentName=\"li\">{`Usage Required`}</strong></li>\n          <li parentName=\"ul\">{`This core prop getter is required to to enable absolute layout for rows`}</li>\n        </ul></li>\n    </ul>\n    <h3 {...{\n      \"id\": \"cell-properties\"\n    }}>{`Cell Properties`}</h3>\n    <ul>\n      <li parentName=\"ul\"><inlineCode parentName=\"li\">{`getCellProps`}</inlineCode><ul parentName=\"li\">\n          <li parentName=\"ul\"><strong parentName=\"li\">{`Usage Required`}</strong></li>\n          <li parentName=\"ul\">{`This core prop getter is required to to enable absolute layout for rows cells`}</li>\n        </ul></li>\n    </ul>\n    <h3 {...{\n      \"id\": \"headergroup-properties\"\n    }}>{`HeaderGroup Properties`}</h3>\n    <ul>\n      <li parentName=\"ul\"><inlineCode parentName=\"li\">{`getHeaderGroupProps`}</inlineCode><ul parentName=\"li\">\n          <li parentName=\"ul\"><strong parentName=\"li\">{`Usage Required`}</strong></li>\n          <li parentName=\"ul\">{`This core prop getter is required to to enable absolute layout for headers`}</li>\n        </ul></li>\n    </ul>\n    <h3 {...{\n      \"id\": \"header-properties\"\n    }}>{`Header Properties`}</h3>\n    <ul>\n      <li parentName=\"ul\"><inlineCode parentName=\"li\">{`getHeaderProps`}</inlineCode><ul parentName=\"li\">\n          <li parentName=\"ul\"><strong parentName=\"li\">{`Usage Required`}</strong></li>\n          <li parentName=\"ul\">{`This core prop getter is required to to enable absolute layout for headers`}</li>\n        </ul></li>\n    </ul>\n    <h3 {...{\n      \"id\": \"example\"\n    }}>{`Example`}</h3>\n    <ul>\n      <li parentName=\"ul\"><a parentName=\"li\" {...{\n          \"href\": \"https://github.com/tannerlinsley/react-table/tree/master/examples/block-layout\"\n        }}>{`Source`}</a></li>\n      <li parentName=\"ul\"><a parentName=\"li\" {...{\n          \"href\": \"https://codesandbox.io/s/github/tannerlinsley/react-table/tree/master/examples/block-layout\"\n        }}>{`Open in CodeSandbox`}</a></li>\n    </ul>\n\n    </MDXLayout>;\n}\n\n;\nMDXContent.isMDXComponent = true;"}}